speakleash/__init__.py
speakleash/config.json
speakleash/config_loader.py
speakleash/contrib.py
speakleash/category_manager/__init__.py
speakleash/category_manager/category_manager.py
speakleash/core/__init__.py
speakleash/core/core.py
speakleash/dataset/__init__.py
speakleash/dataset/dataset.py
speakleash/downloader/__init__.py
speakleash/downloader/structure_downloader.py
speakleash-0.3.51.dist-info/LICENSE
speakleash-0.3.51.dist-info/METADATA
speakleash-0.3.51.dist-info/WHEEL
speakleash-0.3.51.dist-info/top_level.txt
speakleash-0.3.51.dist-info/RECORD
