Metadata-Version: 2.1
Name: speakleash
Version: 0.3.51
Summary: SpeakLeash agnostic dataset for Polish
Home-page: https://github.com/speakleash/speakleash
Author: SpeakLeash Team
Author-email: team@speakleash.org
License: UNKNOWN
Platform: UNKNOWN
Requires-Python: >=3.6
License-File: LICENSE
Requires-Dist: requests
Requires-Dist: tqdm
Requires-Dist: lm-dataformat
